<Page navigatingTo="onNavigatingTo" class="page" xmlns="http://schemas.nativescript.org/tns.xsd" >
    <ActionBar class="action-bar">
        <android>
            <NavigationButton android.systemIcon="ic_menu_back" tap="onBackTap" />
        </android>
    </ActionBar>

    <GridLayout columns="*" rows="auto, auto, *">
        <StackLayout row="0" col="0" class="list-view-section-header"></StackLayout>
        <StackLayout row="1" col="0">
            <GridLayout columns="*, auto" rows="auto" class="list-view-item-form-bottom">
                <Label row="0" col="0" text="Offered to APCIA Members?" class="list-view-item-left" />
                <Switch row="0" col="1" checked="{{ offeredToMembers }}" horizontalAlignment="right" class="switch" />
            </GridLayout>
        </StackLayout>
        <StackLayout row="2" col="0" style="background-color: #eee;"></StackLayout>
    </GridLayout>
</Page>
